win10toast/__init__.py
win10toast/__main__.py
win10toast/data/python.ico
win10toast_for_pip_bigger_10/__init__.py
win10toast_for_pip_bigger_10/__main__.py
win10toast_for_pip_bigger_10-1.0.dist-info/LICENSE
win10toast_for_pip_bigger_10-1.0.dist-info/METADATA
win10toast_for_pip_bigger_10-1.0.dist-info/WHEEL
win10toast_for_pip_bigger_10-1.0.dist-info/top_level.txt
win10toast_for_pip_bigger_10-1.0.dist-info/RECORD
